bayesian/__init__.py
bayesian/samples.py
bayesian/tests.py
Bayesian-0.3.3.dist-info/LICENSE.txt
Bayesian-0.3.3.dist-info/METADATA
Bayesian-0.3.3.dist-info/WHEEL
Bayesian-0.3.3.dist-info/top_level.txt
Bayesian-0.3.3.dist-info/RECORD
