Metadata-Version: 2.1
Name: Bayesian
Version: 0.3.3
Summary: Library and utility module for Bayesian reasoning
Home-page: http://pypi.python.org/pypi/bayesian/
Author: BoppreH
Author-email: boppreh@gmail.com
License: LICENSE.txt
License-File: LICENSE.txt
